modul.py
modul-0.2.0.post0.dist-info/WHEEL
modul-0.2.0.post0.dist-info/METADATA
modul-0.2.0.post0.dist-info/license_files/LICENSE
modul-0.2.0.post0.dist-info/RECORD
