Metadata-Version: 2.1
Name: modul
Version: 0.2.0.post0
Summary: Control the exported members for your modules
License: MIT
Author-email: Frost Ming <mianghong@gmail.com>
Requires-Python: >=3.7
Classifier: Development Status :: 3 - Alpha
Classifier: Programming Language :: Python :: 3.10
Classifier: Programming Language :: Python :: 3.7
Classifier: Programming Language :: Python :: 3.8
Classifier: Programming Language :: Python :: 3.9
Classifier: Programming Language :: Python :: Implementation :: CPython
Classifier: Programming Language :: Python :: Implementation :: PyPy
Project-URL: Homepage, https://github.com/frostming/modul
Project-URL: Repository, https://github.com/frostming/modul
